cloud_dictionary/__init__.py
cloud_dictionary/main.py
cloud_dictionary-2.0.1.dist-info/METADATA
cloud_dictionary-2.0.1.dist-info/WHEEL
cloud_dictionary-2.0.1.dist-info/licenses/LICENSE
cloud_dictionary-2.0.1.dist-info/RECORD
