Metadata-Version: 2.1
Name: cloud_dictionary
Version: 2.0.1
Summary: A DynamoDB implementation of collections.abc.MutableMapping
Project-URL: Homepage, https://github.com/yrom1/cloud-dictionary
Project-URL: Bug Tracker, https://github.com/yrom1/cloud-dictionary/issues
Author-email: Ryan Moore <ryanm.inbox@gmail.com>
License-File: LICENSE
Classifier: License :: OSI Approved :: MIT License
Classifier: Operating System :: OS Independent
Classifier: Programming Language :: Python :: 3
Requires-Python: >=3.10
Requires-Dist: boto3
